ciohoudini/VERSION
ciohoudini/__init__.py
ciohoudini/assets.py
ciohoudini/buttoned_scroll_panel.py
ciohoudini/common.py
ciohoudini/const.py
ciohoudini/context.py
ciohoudini/controller.py
ciohoudini/driver.py
ciohoudini/environment.py
ciohoudini/errors.py
ciohoudini/frames.py
ciohoudini/instances.py
ciohoudini/job_title.py
ciohoudini/miscellaneous.py
ciohoudini/notice_grp.py
ciohoudini/payload.py
ciohoudini/post_install.py
ciohoudini/progress_tab.py
ciohoudini/project.py
ciohoudini/reloader.py
ciohoudini/render_rops.py
ciohoudini/response_tab.py
ciohoudini/software.py
ciohoudini/submission_dialog.py
ciohoudini/submit.py
ciohoudini/takes.py
ciohoudini/task.py
ciohoudini/tooltips.py
ciohoudini/validation.py
ciohoudini/validation_tab.py
ciohoudini/components/__init__.py
ciohoudini/components/buttoned_scroll_panel.py
ciohoudini/components/notice_grp.py
ciohoudini/icons/ConductorError_18x18.png
ciohoudini/icons/ConductorError_24x24.png
ciohoudini/icons/ConductorError_36x36.png
ciohoudini/icons/ConductorError_48x48.png
ciohoudini/icons/ConductorInfo_18x18.png
ciohoudini/icons/ConductorInfo_24x24.png
ciohoudini/icons/ConductorInfo_36x36.png
ciohoudini/icons/ConductorInfo_48x48.png
ciohoudini/icons/ConductorSuccess_18x18.png
ciohoudini/icons/ConductorSuccess_24x24.png
ciohoudini/icons/ConductorSuccess_36x36.png
ciohoudini/icons/ConductorSuccess_48x48.png
ciohoudini/icons/ConductorWarning_18x18.png
ciohoudini/icons/ConductorWarning_24x24.png
ciohoudini/icons/ConductorWarning_36x36.png
ciohoudini/icons/ConductorWarning_48x48.png
ciohoudini/icons/conductor_logo_white.png
ciohoudini/otls/job.hda
ciohoudini/progress/__init__.py
ciohoudini/progress/file_status_panel.py
ciohoudini/progress/file_status_row.py
ciohoudini/progress/jobs_progress_widget.py
ciohoudini/progress/md5_progress_widget.py
ciohoudini/progress/progress_widget_base.py
ciohoudini/progress/submission_worker.py
ciohoudini/progress/upload_progress_widget.py
ciohoudini/scripts/__init__.py
ciohoudini-0.7.15.dist-info/METADATA
ciohoudini-0.7.15.dist-info/WHEEL
ciohoudini-0.7.15.dist-info/top_level.txt
ciohoudini-0.7.15.dist-info/RECORD
