Metadata-Version: 2.1
Name: ciohoudini
Version: 0.7.15
Summary: Houdini submitter hda for the Conductor Cloud Rendering Platform.
Home-page: https://github.com/ConductorTechnologies/ciohoudini
Author: conductor
Author-email: info@conductortech.com
Classifier: Operating System :: OS Independent
Classifier: Programming Language :: Python
Classifier: Topic :: Multimedia :: Graphics :: 3D Rendering
Requires-Dist: ciocore <9.0.0,>=8.2.0
Requires-Dist: ciopath <2.0.0,>=1.1.0
Requires-Dist: cioseq <1.0.0,>=0.5.1
Requires-Dist: ciotemplate <1.0.0,>=0.1.2
Requires-Dist: json-stream <3.0.0,>=2.3.2
